makejob/__init__.py
makejob/bin/__init__.py
makejob/bin/main.py
makejob/core/__init__.py
makejob/core/check_queues.py
makejob/core/job.py
makejob/core/parse.py
makejob/core/util.py
makejob/version/version.json
makejob-1.0.1.dist-info/METADATA
makejob-1.0.1.dist-info/WHEEL
makejob-1.0.1.dist-info/entry_points.txt
makejob-1.0.1.dist-info/top_level.txt
makejob-1.0.1.dist-info/RECORD
